ceml/VERSION
ceml/__init__.py
ceml/backend/__init__.py
ceml/backend/jax/__init__.py
ceml/backend/jax/layer.py
ceml/backend/jax/costfunctions/__init__.py
ceml/backend/jax/costfunctions/costfunctions.py
ceml/backend/jax/costfunctions/losses.py
ceml/backend/jax/preprocessing/__init__.py
ceml/backend/jax/preprocessing/affine_preprocessing.py
ceml/backend/jax/preprocessing/normalizer.py
ceml/backend/jax/preprocessing/pca.py
ceml/backend/jax/preprocessing/polynomial_features.py
ceml/backend/jax/preprocessing/scaler.py
ceml/backend/tensorflow/__init__.py
ceml/backend/tensorflow/layer.py
ceml/backend/tensorflow/costfunctions/__init__.py
ceml/backend/tensorflow/costfunctions/costfunctions.py
ceml/backend/tensorflow/costfunctions/losses.py
ceml/backend/tensorflow/optimizer/__init__.py
ceml/backend/tensorflow/optimizer/optimizer.py
ceml/backend/torch/__init__.py
ceml/backend/torch/layer.py
ceml/backend/torch/costfunctions/__init__.py
ceml/backend/torch/costfunctions/costfunctions.py
ceml/backend/torch/costfunctions/losses.py
ceml/backend/torch/optimizer/__init__.py
ceml/backend/torch/optimizer/optimizer.py
ceml/costfunctions/__init__.py
ceml/costfunctions/costfunctions.py
ceml/model/__init__.py
ceml/model/counterfactual.py
ceml/model/model.py
ceml/optim/__init__.py
ceml/optim/cvx.py
ceml/optim/ga.py
ceml/optim/input_wrapper.py
ceml/optim/optimizer.py
ceml/sklearn/__init__.py
ceml/sklearn/counterfactual.py
ceml/sklearn/decisiontree.py
ceml/sklearn/isolationforest.py
ceml/sklearn/knn.py
ceml/sklearn/lda.py
ceml/sklearn/linearregression.py
ceml/sklearn/lvq.py
ceml/sklearn/models.py
ceml/sklearn/naivebayes.py
ceml/sklearn/pipeline.py
ceml/sklearn/plausibility.py
ceml/sklearn/qda.py
ceml/sklearn/randomforest.py
ceml/sklearn/softmaxregression.py
ceml/sklearn/tree.py
ceml/sklearn/utils.py
ceml/tfkeras/__init__.py
ceml/tfkeras/counterfactual.py
ceml/tfkeras/utils.py
ceml/torch/__init__.py
ceml/torch/counterfactual.py
ceml/torch/utils.py
ceml-0.7.dist-info/LICENSE
ceml-0.7.dist-info/METADATA
ceml-0.7.dist-info/WHEEL
ceml-0.7.dist-info/top_level.txt
ceml-0.7.dist-info/RECORD
