Metadata-Version: 2.1
Name: ceml
Version: 0.7
Summary: Counterfactuals for explaining machine learning models - A Python toolbox
Home-page: https://github.com/andreArtelt/ceml
Author: André Artelt
Author-email: aartelt@techfak.uni-bielefeld.de
License: MIT
Keywords: machine learning counterfactual
Classifier: Development Status :: 4 - Beta
Classifier: Intended Audience :: Science/Research
Classifier: Intended Audience :: Developers
Classifier: License :: OSI Approved :: MIT License
Classifier: Programming Language :: Python :: 3.8
Classifier: Topic :: Scientific/Engineering :: Artificial Intelligence
Requires-Python: >=3.8
License-File: LICENSE
Requires-Dist: sklearn-lvq ==1.1.1
Requires-Dist: scikit-learn ==1.3.1
Requires-Dist: tensorflow ==2.13.1
Requires-Dist: torch ==2.0.1
Requires-Dist: cvxpy ==1.3.2
Requires-Dist: jax ==0.4.13
Requires-Dist: jaxlib ==0.4.13
